hreporting/__init__.py
hreporting/cli.py
hreporting/config.py
hreporting/emails.py
hreporting/harvest_client.py
hreporting/utils.py
tests/hreporting/__init__.py
tests/hreporting/test_emails.py
tests/hreporting/test_harvest_client.py
tests/hreporting/test_utils.py
harvestcli-0.1.1.dist-info/LICENSE
harvestcli-0.1.1.dist-info/METADATA
harvestcli-0.1.1.dist-info/WHEEL
harvestcli-0.1.1.dist-info/entry_points.txt
harvestcli-0.1.1.dist-info/top_level.txt
harvestcli-0.1.1.dist-info/RECORD
