Metadata-Version: 2.1
Name: harvestcli
Version: 0.1.1
Summary: harvestcli - Harvest cli utility for running reports
Home-page: https://github.com/taosmountain/harvest-reporting
Author: TAOS DevopsNow
License: UNKNOWN
Platform: UNKNOWN
Classifier: Programming Language :: Python :: 3
Classifier: License :: OSI Approved :: GNU General Public License v3 (GPLv3)
Classifier: Operating System :: OS Independent
Requires-Dist: Click (>=7.0)
Requires-Dist: colorama (>=0.4)
Requires-Dist: PyYAML (>=5.1)
Requires-Dist: requests (>=2.22)
Requires-Dist: sendgrid (>=6.2)
